funcnodes_sklearn/__init__.py
funcnodes_sklearn/_utils.py
funcnodes_sklearn/calibration.py
funcnodes_sklearn/cluster.py
funcnodes_sklearn/covariance.py
funcnodes_sklearn/cross_decomposition.py
funcnodes_sklearn/datasets.py
funcnodes_sklearn/decomposition.py
funcnodes_sklearn/discriminant_analysis.py
funcnodes_sklearn/fit.py
funcnodes_sklearn/metrics.py
funcnodes_sklearn/preprocessing.py
funcnodes_sklearn-0.1.15.dist-info/LICENSE
funcnodes_sklearn-0.1.15.dist-info/METADATA
funcnodes_sklearn-0.1.15.dist-info/WHEEL
funcnodes_sklearn-0.1.15.dist-info/entry_points.txt
funcnodes_sklearn-0.1.15.dist-info/top_level.txt
funcnodes_sklearn-0.1.15.dist-info/RECORD
