Metadata-Version: 2.2
Name: funcnodes-sklearn
Version: 0.1.15
Summary: Funcnodes interface to scikit-learn
Author-email: Kourosh Rezaei <kouroshrezaei90@gmail.com>
License: AGPL-3.0
Project-URL: homepage, https://github.com/Linkdlab/funcnodes_sklearn
Project-URL: source, https://github.com/Linkdlab/funcnodes_sklearn
Project-URL: tracker, https://github.com/Linkdlab/funcnodes_sklearn/issues
Project-URL: download, https://pypi.org/project/funcnodes-sklearn/#files
Requires-Python: >=3.11
License-File: LICENSE
Requires-Dist: scikit-learn>=1.4.2
Requires-Dist: funcnodes
Requires-Dist: funcnodes-pandas
Requires-Dist: funcnodes-numpy
